flask_bootstrap/__init__.py
flask_bootstrap/static/.DS_Store
flask_bootstrap/static/bootstrap4/.DS_Store
flask_bootstrap/static/bootstrap4/jquery.min.js
flask_bootstrap/static/bootstrap4/jquery.min.map
flask_bootstrap/static/bootstrap4/css/.DS_Store
flask_bootstrap/static/bootstrap4/css/bootstrap.min.css
flask_bootstrap/static/bootstrap4/css/bootstrap.min.css.map
flask_bootstrap/static/bootstrap4/css/bootswatch/.DS_Store
flask_bootstrap/static/bootstrap4/css/bootswatch/cerulean/_bootswatch.scss
flask_bootstrap/static/bootstrap4/css/bootswatch/cerulean/_variables.scss
flask_bootstrap/static/bootstrap4/css/bootswatch/cerulean/bootstrap.css
flask_bootstrap/static/bootstrap4/css/bootswatch/cerulean/bootstrap.min.css
flask_bootstrap/static/bootstrap4/css/bootswatch/cosmo/_bootswatch.scss
flask_bootstrap/static/bootstrap4/css/bootswatch/cosmo/_variables.scss
flask_bootstrap/static/bootstrap4/css/bootswatch/cosmo/bootstrap.css
flask_bootstrap/static/bootstrap4/css/bootswatch/cosmo/bootstrap.min.css
flask_bootstrap/static/bootstrap4/css/bootswatch/cyborg/_bootswatch.scss
flask_bootstrap/static/bootstrap4/css/bootswatch/cyborg/_variables.scss
flask_bootstrap/static/bootstrap4/css/bootswatch/cyborg/bootstrap.css
flask_bootstrap/static/bootstrap4/css/bootswatch/cyborg/bootstrap.min.css
flask_bootstrap/static/bootstrap4/css/bootswatch/darkly/_bootswatch.scss
flask_bootstrap/static/bootstrap4/css/bootswatch/darkly/_variables.scss
flask_bootstrap/static/bootstrap4/css/bootswatch/darkly/bootstrap.css
flask_bootstrap/static/bootstrap4/css/bootswatch/darkly/bootstrap.min.css
flask_bootstrap/static/bootstrap4/css/bootswatch/flatly/_bootswatch.scss
flask_bootstrap/static/bootstrap4/css/bootswatch/flatly/_variables.scss
flask_bootstrap/static/bootstrap4/css/bootswatch/flatly/bootstrap.css
flask_bootstrap/static/bootstrap4/css/bootswatch/flatly/bootstrap.min.css
flask_bootstrap/static/bootstrap4/css/bootswatch/journal/_bootswatch.scss
Bootstrap_Flask-2.3.2.dist-info/LICENSE
Bootstrap_Flask-2.3.2.dist-info/METADATA
Bootstrap_Flask-2.3.2.dist-info/WHEEL
Bootstrap_Flask-2.3.2.dist-info/top_level.txt
Bootstrap_Flask-2.3.2.dist-info/RECORD
